swanoauthrenew/__init__.py
swanoauthrenew/_version.py
swanoauthrenew/swanoauthrenew.py
swanoauthrenew-1.0.2.data/data/etc/jupyter/jupyter_server_config.d/swanoauthrenew.json
swanoauthrenew-1.0.2.dist-info/METADATA
swanoauthrenew-1.0.2.dist-info/WHEEL
swanoauthrenew-1.0.2.dist-info/top_level.txt
swanoauthrenew-1.0.2.dist-info/RECORD
